proxiestor/__init__.py
proxiestor/pytor.cpp
proxiestor/setup.py
proxiestor-2.0.dist-info/LICENSE.txt
proxiestor-2.0.dist-info/METADATA
proxiestor-2.0.dist-info/WHEEL
proxiestor-2.0.dist-info/entry_points.txt
proxiestor-2.0.dist-info/top_level.txt
proxiestor-2.0.dist-info/RECORD
