Metadata-Version: 2.1
Name: proxiestor
Version: 2.0
Summary: Automate Tor Ip Rotation
Home-page: https://github.com/sptty-chan/proxiestor
Author: Sptty Chan
Author-email: sptty_chan@ccmail.uk
License: MIT
Platform: UNKNOWN
Classifier: Development Status :: 3 - Alpha
Classifier: Intended Audience :: Developers
Classifier: Topic :: Software Development :: Build Tools
Classifier: License :: OSI Approved :: MIT License
Classifier: Programming Language :: Python :: 3
Requires-Python: >=3
License-File: LICENSE.txt
Requires-Dist: stem (==1.8.0)
Requires-Dist: psutil (==5.9.6)
Requires-Dist: cython (==0.29.33)
